BlobTrigger2/__init__.py
common/__init__.py
common/applogger/__init__.py
common/applogger/logger.py
common/constants/__init__.py
common/constants/app_status.py
common/constants/custom_log.py
common/constants/error_response.py
common/constants/response_message.py
common/constants/shared_constants.py
common/constants/success_response.py
common/db/__init__.py
common/db/data_access.py
common/patterns/__init__.py
common/patterns/singleton.py
common/policy/__init__.py
common/swagger/__init__.py
common/token/__init__.py
common/token/token_descriptor.py
common/token/tokengen.py
common/utilities/__init__.py
common/utilities/json_helper.py
common/utilities/set_properties.py
common/validate/__init__.py
common/validate/validation_helper.py
commonmarmallikarjunagoud2/__init__.py
commonmarmallikarjunagoud2/applogger/__init__.py
commonmarmallikarjunagoud2/applogger/logger.py
commonmarmallikarjunagoud2/constants/__init__.py
commonmarmallikarjunagoud2/constants/app_status.py
commonmarmallikarjunagoud2/constants/custom_log.py
commonmarmallikarjunagoud2/constants/error_response.py
commonmarmallikarjunagoud2/constants/response_message.py
commonmarmallikarjunagoud2/constants/shared_constants.py
commonmarmallikarjunagoud2/constants/success_response.py
commonmarmallikarjunagoud2/db/__init__.py
commonmarmallikarjunagoud2/db/data_access.py
commonmarmallikarjunagoud2/patterns/__init__.py
commonmarmallikarjunagoud2/patterns/singleton.py
commonmarmallikarjunagoud2/policy/__init__.py
commonmarmallikarjunagoud2/swagger/__init__.py
commonmarmallikarjunagoud2/token/__init__.py
commonmarmallikarjunagoud2/token/token_descriptor.py
commonmarmallikarjunagoud2/token/tokengen.py
commonmarmallikarjunagoud2/utilities/__init__.py
commonmarmallikarjunagoud2/utilities/json_helper.py
commonmarmallikarjunagoud2/utilities/set_properties.py
commonmarmallikarjunagoud2/validate/__init__.py
commonmarmallikarjunagoud2/validate/validation_helper.py
getFileStatus/__init__.py
getFileStatus/businesslogic/__init__.py
commonmarmallikarjunagoud2-0.0.1.dist-info/METADATA
commonmarmallikarjunagoud2-0.0.1.dist-info/WHEEL
commonmarmallikarjunagoud2-0.0.1.dist-info/top_level.txt
commonmarmallikarjunagoud2-0.0.1.dist-info/RECORD
